{
    "created_but_not_ready_pods": [
        "a-deployment-76ff5bd997-4ch27",
        "a-deployment-76ff5bd997-4gcgf",
        "a-deployment-76ff5bd997-4gt99",
        "a-deployment-76ff5bd997-4j4qz",
        "a-deployment-76ff5bd997-7h7ct",
        "a-deployment-76ff5bd997-7smld",
        "a-deployment-76ff5bd997-87vxp",
        "a-deployment-76ff5bd997-8d6bh",
        "a-deployment-76ff5bd997-9f4p8",
        "a-deployment-76ff5bd997-b52mn",
        "a-deployment-76ff5bd997-dbwdw",
        "a-deployment-76ff5bd997-dkxz8",
        "a-deployment-76ff5bd997-dm62f",
        "a-deployment-76ff5bd997-drddr",
        "a-deployment-76ff5bd997-dvb9x",
        "a-deployment-76ff5bd997-dxxsf",
        "a-deployment-76ff5bd997-f7mtj",
        "a-deployment-76ff5bd997-fhvl6",
        "a-deployment-76ff5bd997-ghwmc",
        "a-deployment-76ff5bd997-gv8vq",
        "a-deployment-76ff5bd997-jpdqx",
        "a-deployment-76ff5bd997-llg7b",
        "a-deployment-76ff5bd997-m8chf",
        "a-deployment-76ff5bd997-m8cxk",
        "a-deployment-76ff5bd997-mgq9j",
        "a-deployment-76ff5bd997-mprt5",
        "a-deployment-76ff5bd997-mqw54",
        "a-deployment-76ff5bd997-mvmnd",
        "a-deployment-76ff5bd997-nc9gt",
        "a-deployment-76ff5bd997-nwgrg",
        "a-deployment-76ff5bd997-pc4vz",
        "a-deployment-76ff5bd997-pgx46",
        "a-deployment-76ff5bd997-pw46n",
        "a-deployment-76ff5bd997-pw6sx",
        "a-deployment-76ff5bd997-pzn4t",
        "a-deployment-76ff5bd997-qpjks",
        "a-deployment-76ff5bd997-qr8x8",
        "a-deployment-76ff5bd997-rwgmz",
        "a-deployment-76ff5bd997-tcnj8",
        "a-deployment-76ff5bd997-trgs5",
        "a-deployment-76ff5bd997-vtxns",
        "a-deployment-76ff5bd997-wl7fp",
        "a-deployment-76ff5bd997-wvg62",
        "a-deployment-76ff5bd997-zhnrx",
        "a-deployment-76ff5bd997-zrndq",
        "a-deployment-76ff5bd997-zvbn5",
        "c-deployment-568986b69f-6drmx",
        "c-deployment-568986b69f-94kqd",
        "c-deployment-568986b69f-gtq6p",
        "c-deployment-568986b69f-kbxtv",
        "d-deployment-5c8b9cd676-7tnv2",
        "d-deployment-5c8b9cd676-mwths"
    ],
    "ready_pod_duration": {
        "a-deployment-76ff5bd997-6vpbm": "1.7109692220000001s",
        "a-deployment-76ff5bd997-8gcfn": "1.710969252s",
        "a-deployment-76ff5bd997-jstc5": "1.7109692220000001s",
        "a-deployment-76ff5bd997-r6m8x": "1.71096369s",
        "a-deployment-76ff5bd997-rr5ph": "1.7109692509999999s",
        "a-deployment-76ff5bd997-sm4sz": "1.7109691470000001s",
        "b-deployment-8686f88b48-2z7dh": "1.710969478s",
        "b-deployment-8686f88b48-9rp8l": "1.7109695999999999s",
        "b-deployment-8686f88b48-bhnp2": "1.710969493s",
        "b-deployment-8686f88b48-c7vpq": "1.710969522s",
        "b-deployment-8686f88b48-qqtg2": "1.710969599s",
        "b-deployment-8686f88b48-swtkm": "1.710957421s",
        "c-deployment-568986b69f-4k9zp": "1.7109700399999999s",
        "c-deployment-568986b69f-9hz9k": "1.710969855s",
        "c-deployment-568986b69f-bh25n": "1.710969749s",
        "c-deployment-568986b69f-c226s": "1.710969959s",
        "c-deployment-568986b69f-fjx7c": "1.7109701240000001s",
        "c-deployment-568986b69f-hpx7h": "1.710962518s",
        "c-deployment-568986b69f-lhclj": "1.7109698089999998s",
        "c-deployment-568986b69f-phvdd": "1.710969148s",
        "c-deployment-568986b69f-qjshn": "1.710969855s",
        "c-deployment-568986b69f-rwrmr": "1.7109697640000001s",
        "d-deployment-5c8b9cd676-55wpp": "1.710957422s",
        "d-deployment-5c8b9cd676-754cg": "1.7109701s",
        "d-deployment-5c8b9cd676-rvs59": "1.710970063s",
        "d-deployment-5c8b9cd676-wrsdl": "1.710970019s",
        "ecmus-scheduler-6cc4c7db4c-8lg7s": "1.710968804s"
    }
}