{
    "created_but_not_ready_pods": [
        "a-deployment-7989fcfbfd-456xk",
        "a-deployment-7989fcfbfd-57l4k",
        "a-deployment-7989fcfbfd-745zk",
        "a-deployment-7989fcfbfd-7qskv",
        "a-deployment-7989fcfbfd-7sl2d",
        "a-deployment-7989fcfbfd-8nvkb",
        "a-deployment-7989fcfbfd-96k4l",
        "a-deployment-7989fcfbfd-9cg2w",
        "a-deployment-7989fcfbfd-9dgxb",
        "a-deployment-7989fcfbfd-9gkl8",
        "a-deployment-7989fcfbfd-dm49n",
        "a-deployment-7989fcfbfd-f4h5x",
        "a-deployment-7989fcfbfd-gz986",
        "a-deployment-7989fcfbfd-j5l8k",
        "a-deployment-7989fcfbfd-kqxdm",
        "a-deployment-7989fcfbfd-q6d2w",
        "a-deployment-7989fcfbfd-shr9v",
        "a-deployment-7989fcfbfd-t9lct",
        "a-deployment-7989fcfbfd-v82bc",
        "a-deployment-7989fcfbfd-vdcgq",
        "a-deployment-7989fcfbfd-w4lcm",
        "a-deployment-7989fcfbfd-wbbgm",
        "a-deployment-7989fcfbfd-xfmfn",
        "c-deployment-7954dd5668-2r7hz",
        "c-deployment-7954dd5668-fg74c",
        "c-deployment-7954dd5668-fn692",
        "c-deployment-7954dd5668-gjkvl",
        "c-deployment-7954dd5668-lr9bg",
        "c-deployment-7954dd5668-mpm8p",
        "c-deployment-7954dd5668-s4zzj"
    ],
    "ready_pod_duration": {
        "a-deployment-7989fcfbfd-2tt69": "1.710771241s",
        "a-deployment-7989fcfbfd-4g6ng": "1.7107719019999998s",
        "a-deployment-7989fcfbfd-5nv4g": "1.7107711509999999s",
        "a-deployment-7989fcfbfd-8ndh5": "1.7107711810000001s",
        "a-deployment-7989fcfbfd-98tc2": "1.710771692s",
        "a-deployment-7989fcfbfd-ddk5t": "1.710770971s",
        "a-deployment-7989fcfbfd-fg9gj": "1.7107695729999999s",
        "a-deployment-7989fcfbfd-gq266": "1.710771046s",
        "a-deployment-7989fcfbfd-hcnbr": "1.7107717070000001s",
        "a-deployment-7989fcfbfd-hjl94": "1.7107711509999999s",
        "a-deployment-7989fcfbfd-hl8cc": "1.710771046s",
        "a-deployment-7989fcfbfd-hrj6f": "1.710771917s",
        "a-deployment-7989fcfbfd-hxztt": "1.710771692s",
        "a-deployment-7989fcfbfd-jqgx4": "1.710771307s",
        "a-deployment-7989fcfbfd-kpm8x": "1.7107710900000002s",
        "a-deployment-7989fcfbfd-p2qwg": "1.7107716210000001s",
        "a-deployment-7989fcfbfd-srsjl": "1.710771241s",
        "a-deployment-7989fcfbfd-wz4jf": "1.7107717070000001s",
        "b-deployment-68f688df8c-fwtqg": "1.710768162s",
        "c-deployment-7954dd5668-6tbl2": "1.7107717359999999s",
        "c-deployment-7954dd5668-7mlgm": "1.710771306s",
        "c-deployment-7954dd5668-7vndf": "1.710768898s",
        "c-deployment-7954dd5668-d8k7l": "1.7107717180000002s",
        "c-deployment-7954dd5668-nrljr": "1.710770971s",
        "c-deployment-7954dd5668-zblts": "1.7107716210000001s",
        "d-deployment-7b4776f58c-69862": "1.710770519s",
        "ecmus-scheduler-844fb69754-4wjfl": "1.710770636s"
    }
}