{
    "created_but_not_ready_pods": [],
    "ready_pod_duration": {
        "a-deployment-5dd4845b6-4d5vz": "1.712474069s",
        "a-deployment-5dd4845b6-4m9r8": "1.7124733779999999s",
        "a-deployment-5dd4845b6-4ngcd": "1.712473663s",
        "a-deployment-5dd4845b6-6m7d7": "1.712473949s",
        "a-deployment-5dd4845b6-8jwcq": "1.712473829s",
        "a-deployment-5dd4845b6-fnpld": "1.712473873s",
        "a-deployment-5dd4845b6-fr5h2": "1.712473829s",
        "a-deployment-5dd4845b6-g9m89": "1.712473799s",
        "a-deployment-5dd4845b6-glfzk": "1.712474189s",
        "a-deployment-5dd4845b6-jpx64": "1.7124733779999999s",
        "a-deployment-5dd4845b6-m5x5b": "1.712474174s",
        "a-deployment-5dd4845b6-mnp2k": "1.712473829s",
        "a-deployment-5dd4845b6-rgphm": "1.712474189s",
        "a-deployment-5dd4845b6-t5bjh": "1.712473137s",
        "a-deployment-5dd4845b6-tlpcm": "1.712474204s",
        "a-deployment-5dd4845b6-wsxsc": "1.712473663s",
        "a-deployment-5dd4845b6-xhmb4": "1.7124733619999999s",
        "a-deployment-5dd4845b6-xspb7": "1.712473393s",
        "a-deployment-5dd4845b6-zdbfj": "1.712474204s",
        "a-deployment-5dd4845b6-zgqbk": "1.712473633s",
        "a-deployment-5dd4845b6-zlj8j": "1.7124739180000002s",
        "a-deployment-5dd4845b6-zxckq": "1.712473393s",
        "b-deployment-6f48785b67-4r5sr": "1.712474114s",
        "b-deployment-6f48785b67-jfqc2": "1.712473137s",
        "b-deployment-6f48785b67-wrjpc": "1.712473302s",
        "c-deployment-97bb96644-27tfs": "1.712473393s",
        "c-deployment-97bb96644-8nd6p": "1.712473543s",
        "c-deployment-97bb96644-926tk": "1.712473768s",
        "c-deployment-97bb96644-9xx4b": "1.7124740840000001s",
        "c-deployment-97bb96644-b8hzs": "1.712473393s",
        "c-deployment-97bb96644-f9tnh": "1.712474024s",
        "c-deployment-97bb96644-gbmf9": "1.7124733779999999s",
        "c-deployment-97bb96644-gm4c4": "1.7124735580000001s",
        "c-deployment-97bb96644-h92xt": "1.712473738s",
        "c-deployment-97bb96644-hgn84": "1.712473588s",
        "c-deployment-97bb96644-hswgg": "1.712473363s",
        "c-deployment-97bb96644-qxz7h": "1.712473543s",
        "c-deployment-97bb96644-qzhzs": "1.712473738s",
        "c-deployment-97bb96644-rq8sz": "1.712474114s",
        "c-deployment-97bb96644-t57vn": "1.7124740090000001s",
        "c-deployment-97bb96644-vsnpq": "1.712473573s",
        "c-deployment-97bb96644-vzgtd": "1.712473994s",
        "c-deployment-97bb96644-wj2nq": "1.712473137s",
        "c-deployment-97bb96644-z6jdn": "1.712474264s",
        "d-deployment-6b754545ff-fmvpw": "1.712473137s",
        "d-deployment-6b754545ff-plfml": "1.712473303s",
        "resource-offset-h6bzn": "1.712473139s",
        "resource-offset-x57cb": "1.712473139s",
        "resource-offset-xrrmg": "1.712473139s"
    }
}