{
    "created_but_not_ready_pods": [],
    "ready_pod_duration": {
        "a-deployment-5dd4845b6-24nk9": "1.7124686009999999s",
        "a-deployment-5dd4845b6-2nvn8": "1.712468451s",
        "a-deployment-5dd4845b6-64l7h": "1.7124686009999999s",
        "a-deployment-5dd4845b6-7h7d8": "1.712468856s",
        "a-deployment-5dd4845b6-9mhgv": "1.7124690070000002s",
        "a-deployment-5dd4845b6-cbmdq": "1.712468947s",
        "a-deployment-5dd4845b6-dmffc": "1.712468946s",
        "a-deployment-5dd4845b6-dwdsm": "1.712469577s",
        "a-deployment-5dd4845b6-gc6v6": "1.712468976s",
        "a-deployment-5dd4845b6-h4t6h": "1.7124686310000001s",
        "a-deployment-5dd4845b6-h9hdw": "1.712468977s",
        "a-deployment-5dd4845b6-kwwhp": "1.712469487s",
        "b-deployment-6f48785b67-2fzx5": "1.712469412s",
        "b-deployment-6f48785b67-4txnk": "1.7124690660000002s",
        "b-deployment-6f48785b67-6s5kz": "1.712469051s",
        "b-deployment-6f48785b67-b2kfc": "1.712468451s",
        "b-deployment-6f48785b67-c2nk7": "1.712469322s",
        "b-deployment-6f48785b67-cjj8d": "1.7124686759999999s",
        "b-deployment-6f48785b67-gxwxm": "1.7124690660000002s",
        "c-deployment-97bb96644-26npc": "1.7124686009999999s",
        "c-deployment-97bb96644-27zw6": "1.7124686310000001s",
        "c-deployment-97bb96644-4m7z9": "1.712468451s",
        "c-deployment-97bb96644-8pfb9": "1.712469397s",
        "c-deployment-97bb96644-dqnmp": "1.7124686310000001s",
        "c-deployment-97bb96644-gwvzw": "1.7124686310000001s",
        "c-deployment-97bb96644-lc7h2": "1.7124686009999999s",
        "c-deployment-97bb96644-rtkm8": "1.712468857s",
        "d-deployment-6b754545ff-4nrmw": "1.712468451s",
        "resource-offset-d97h8": "1.712468453s",
        "resource-offset-nkxrl": "1.712468453s",
        "resource-offset-xmwgs": "1.712468453s"
    }
}